Metadata-Version: 2.1
Name: skill-wordnet
Version: 0.2.2
Summary: ovos Wordnet skill plugin
Home-page: https://github.com/OpenVoiceOS/ovos-skill-wordnet
Author: JarbasAi
Author-email: jarbasai@mailfence.com
License: Apache-2.0
Keywords: ovos skill plugin
License-File: LICENSE
Requires-Dist: ovos-utils<1.0.0,>=0.0.35
Requires-Dist: ovos-workshop<4.0.0,>=3.3.0
Requires-Dist: ovos-translate-server-plugin
Requires-Dist: ovos-config<2.0.0,>=0.0.11
Requires-Dist: ovos-plugin-manager<1.0.0,>=0.0.26
